danish05/__init__.py
danish05/info.py
danish05-0.0.7.dist-info/licenses/LICENSE
danish05-0.0.7.dist-info/WHEEL
danish05-0.0.7.dist-info/METADATA
danish05-0.0.7.dist-info/RECORD
