Metadata-Version: 2.4
Name: danish05
Version: 0.0.7
Summary: # My Social media
Author: Danish05
License-Expression: MIT
License-File: LICENSE
Requires-Dist: rembg
Requires-Dist: onnxruntime
Requires-Dist: opencv-python
Requires-Dist: numpy
Requires-Dist: Pillow
